{
  "v": 1,
  "song_id": "W-d2FbBr",
  "song_title": "Alag Aasmaan",
  "song_artist": "Anuv Jain",
  "language": "hindi",
  "cached_at": "2026-03-15T20:19:35.339Z",
  "recommendations": [
    {
      "id": "4GGV39K7",
      "title": "Baarishein",
      "subtitle": "Anuv Jain",
      "header_desc": "",
      "type": "song",
      "perma_url": "https://www.jiosaavn.com/s/song/hindi/baarishein/baarishein/RC8sZ0cJfAQ",
      "image": "https://c.saavncdn.com/520/Baarishein-English-2018-20180522204131-150x150.webp",
      "language": "hindi",
      "year": "2018",
      "play_count": "17966712",
      "explicit_content": "",
      "list_count": "",
      "list_type": "",
      "list": "",
      "more_info": {
        "music": "",
        "album_id": "12921656",
        "album": "Baarishein",
        "label": "Anuv Jain",
        "label_id": "",
        "origin": "search",
        "is_dolby_content": false,
        "320kbps": "true",
        "encrypted_media_url": "ID2ieOjCrwfgWvL5sXl4B1ImC5QfbsDyd84WcuQyNXLo8CthCIdSrs5a94xC92F6BEQRbRXaESeCYUGa0+FumBw7tS9a8Gtq",
        "encrypted_cache_url": "",
        "encrypted_drm_cache_url": "",
        "encrypted_drm_media_url": "ID2ieOjCrwdjlkMElYlzWCptgNdUpWD8hkyAaE2Hzo/5j93/JuQEL5C2ErK7/23npZ2ww/FP9BkE1OSBJuNpaY92mytrdt3FDnQW0nglPS4=",
        "album_url": "https://www.jiosaavn.com/s/album/hindi/baarishein-2018/,GNiGMi7cx4_",
        "duration": "207",
        "rights": {
          "code": "1",
          "cacheable": "true",
          "delete_cached_object": "",
          "reason": "Pro Only"
        },
        "cache_state": "false",
        "has_lyrics": "false",
        "lyrics_snippet": "",
        "starred": "false",
        "copyright_text": "© 2018 Anuv Jain",
        "artistMap": {
          "primary_artists": [],
          "featured_artists": [],
          "artists": []
        }
      },
      "release_date": "",
      "label_url": "/label/anuv-jain-albums/",
      "triller_available": false,
      "request_jiotune_flag": false,
      "webp": "true",
      "lyrics_id": "",
      "button_tooltip_info": [],
      "downloadUrl": [
        {
          "quality": "320kbps",
          "url": "https://aac.saavncdn.com/520/060f65240088865166a061f2942ef92e_320.mp4"
        },
        {
          "quality": "160kbps",
          "url": "https://aac.saavncdn.com/520/060f65240088865166a061f2942ef92e_160.mp4"
        },
        {
          "quality": "96kbps",
          "url": "https://aac.saavncdn.com/520/060f65240088865166a061f2942ef92e_96.mp4"
        },
        {
          "quality": "48kbps",
          "url": "https://aac.saavncdn.com/520/060f65240088865166a061f2942ef92e_48.mp4"
        },
        {
          "quality": "12kbps",
          "url": "https://aac.saavncdn.com/520/060f65240088865166a061f2942ef92e_12.mp4"
        }
      ],
      "name": "Baarishein",
      "artist": "Anuv Jain",
      "album": "Baarishein",
      "primary_artists": "Anuv Jain",
      "duration": "207",
      "encrypted_media_url": "ID2ieOjCrwfgWvL5sXl4B1ImC5QfbsDyd84WcuQyNXLo8CthCIdSrs5a94xC92F6BEQRbRXaESeCYUGa0+FumBw7tS9a8Gtq"
    },
    {
      "id": "X0zxHHfs",
      "title": "Husn",
      "subtitle": "Anuv Jain",
      "header_desc": "",
      "type": "song",
      "perma_url": "https://www.jiosaavn.com/s/song/hindi/husn/husn/KFgRSTx4UUA",
      "image": "https://c.saavncdn.com/436/Husn-Hindi-2023-20231129054140-150x150.webp",
      "language": "hindi",
      "year": "2023",
      "play_count": "45011711",
      "explicit_content": "",
      "list_count": "",
      "list_type": "",
      "list": "",
      "more_info": {
        "music": "Anuv Jain",
        "album_id": "50076157",
        "album": "Husn",
        "label": "Universal Music India Pvt. Ltd. (on behalf of Anuv Jain)",
        "label_id": "",
        "origin": "search",
        "is_dolby_content": false,
        "320kbps": "true",
        "encrypted_media_url": "ID2ieOjCrwfgWvL5sXl4B1ImC5QfbsDyYBsoAMj6HlWpxq5J+zpePW+VBkRuGH/pHhONaqsaSNdn4TS81ZkB7Bw7tS9a8Gtq",
        "encrypted_cache_url": "",
        "encrypted_drm_cache_url": "",
        "encrypted_drm_media_url": "ID2ieOjCrwdjlkMElYlzWCptgNdUpWD8CyehlnFRc5d7mCgeIFQP7v/d+nrF0L8z03z3J+dNJhdnzIRO8gmVrI92mytrdt3FDnQW0nglPS4=",
        "album_url": "https://www.jiosaavn.com/s/album/hindi/husn-2023/BPrmo21C3cA_",
        "duration": "217",
        "rights": {
          "code": "1",
          "cacheable": "true",
          "delete_cached_object": "",
          "reason": "Pro Only"
        },
        "cache_state": "false",
        "has_lyrics": "false",
        "lyrics_snippet": "",
        "starred": "false",
        "copyright_text": "℗ 2023 Anuv Jain",
        "artistMap": {
          "primary_artists": [],
          "featured_artists": [],
          "artists": []
        }
      },
      "release_date": "",
      "label_url": "/label/universal-music-india-pvt.-ltd.-on-behalf-of-anuv-jain-albums/",
      "triller_available": false,
      "request_jiotune_flag": false,
      "webp": "true",
      "lyrics_id": "",
      "button_tooltip_info": [],
      "downloadUrl": [
        {
          "quality": "320kbps",
          "url": "https://aac.saavncdn.com/436/13795b7aa2e87393366162b9e6a6fe88_320.mp4"
        },
        {
          "quality": "160kbps",
          "url": "https://aac.saavncdn.com/436/13795b7aa2e87393366162b9e6a6fe88_160.mp4"
        },
        {
          "quality": "96kbps",
          "url": "https://aac.saavncdn.com/436/13795b7aa2e87393366162b9e6a6fe88_96.mp4"
        },
        {
          "quality": "48kbps",
          "url": "https://aac.saavncdn.com/436/13795b7aa2e87393366162b9e6a6fe88_48.mp4"
        },
        {
          "quality": "12kbps",
          "url": "https://aac.saavncdn.com/436/13795b7aa2e87393366162b9e6a6fe88_12.mp4"
        }
      ],
      "name": "Husn",
      "artist": "Anuv Jain",
      "album": "Husn",
      "primary_artists": "Anuv Jain",
      "duration": "217",
      "encrypted_media_url": "ID2ieOjCrwfgWvL5sXl4B1ImC5QfbsDyYBsoAMj6HlWpxq5J+zpePW+VBkRuGH/pHhONaqsaSNdn4TS81ZkB7Bw7tS9a8Gtq"
    },
    {
      "id": "zND_RkED",
      "title": "Jo Tum Mere Ho",
      "subtitle": "Anuv Jain",
      "header_desc": "",
      "type": "song",
      "perma_url": "https://www.jiosaavn.com/s/song/hindi/jo-tum-mere-ho/jo-tum-mere-ho/CiYvbiZbcnc",
      "image": "https://c.saavncdn.com/401/Jo-Tum-Mere-Ho-Hindi-2024-20240731053953-150x150.webp",
      "language": "hindi",
      "year": "2024",
      "play_count": "53411597",
      "explicit_content": "",
      "list_count": "",
      "list_type": "",
      "list": "",
      "more_info": {
        "music": "Anuv Jain",
        "album_id": "56692135",
        "album": "Jo Tum Mere Ho",
        "label": "Universal Music India Pvt. Ltd. (on behalf of Anuv Jain)",
        "label_id": "",
        "origin": "search",
        "is_dolby_content": false,
        "320kbps": "true",
        "encrypted_media_url": "ID2ieOjCrwfgWvL5sXl4B1ImC5QfbsDyud33Lr1tZlHaFZfErrkmR1cXkyniriIFwNSzTuTiIT+aj0TJTsn4+Bw7tS9a8Gtq",
        "encrypted_cache_url": "",
        "encrypted_drm_cache_url": "",
        "encrypted_drm_media_url": "ID2ieOjCrwdjlkMElYlzWCptgNdUpWD817LlAjjyh5jL7XtrVJ9KeBozRAOCwkl40PPPpjEpL/qVua2l/WdyOo92mytrdt3FDnQW0nglPS4=",
        "album_url": "https://www.jiosaavn.com/s/album/hindi/jo-tum-mere-ho-2024/KxURLGjeQg4_",
        "duration": "252",
        "rights": {
          "code": "1",
          "cacheable": "true",
          "delete_cached_object": "",
          "reason": "Pro Only"
        },
        "cache_state": "false",
        "has_lyrics": "false",
        "lyrics_snippet": "",
        "starred": "false",
        "copyright_text": "℗ 2024 Anuv Jain",
        "artistMap": {
          "primary_artists": [],
          "featured_artists": [],
          "artists": []
        }
      },
      "release_date": "",
      "label_url": "/label/universal-music-india-pvt.-ltd.-on-behalf-of-anuv-jain-albums/",
      "triller_available": false,
      "request_jiotune_flag": false,
      "webp": "true",
      "lyrics_id": "",
      "button_tooltip_info": [],
      "downloadUrl": [
        {
          "quality": "320kbps",
          "url": "https://aac.saavncdn.com/401/1e4444c13f76ac543c19b01d7ea0423a_320.mp4"
        },
        {
          "quality": "160kbps",
          "url": "https://aac.saavncdn.com/401/1e4444c13f76ac543c19b01d7ea0423a_160.mp4"
        },
        {
          "quality": "96kbps",
          "url": "https://aac.saavncdn.com/401/1e4444c13f76ac543c19b01d7ea0423a_96.mp4"
        },
        {
          "quality": "48kbps",
          "url": "https://aac.saavncdn.com/401/1e4444c13f76ac543c19b01d7ea0423a_48.mp4"
        },
        {
          "quality": "12kbps",
          "url": "https://aac.saavncdn.com/401/1e4444c13f76ac543c19b01d7ea0423a_12.mp4"
        }
      ],
      "name": "Jo Tum Mere Ho",
      "artist": "Anuv Jain",
      "album": "Jo Tum Mere Ho",
      "primary_artists": "Anuv Jain",
      "duration": "252",
      "encrypted_media_url": "ID2ieOjCrwfgWvL5sXl4B1ImC5QfbsDyud33Lr1tZlHaFZfErrkmR1cXkyniriIFwNSzTuTiIT+aj0TJTsn4+Bw7tS9a8Gtq"
    },
    {
      "id": "FC63n6XV",
      "title": "Kya Mujhe Pyar Hai",
      "subtitle": "Pritam, KK",
      "header_desc": "",
      "type": "song",
      "perma_url": "https://www.jiosaavn.com/s/song/hindi/woh-lamhe/kya-mujhe-pyar-hai/NitdAhoGb2U",
      "image": "https://c.saavncdn.com/832/Woh-Lamhe-Hindi-2006-20241223151332-150x150.webp",
      "language": "hindi",
      "year": "2006",
      "play_count": "50380857",
      "explicit_content": "",
      "list_count": "",
      "list_type": "",
      "list": "",
      "more_info": {
        "music": "Pritam",
        "album_id": "1054258",
        "album": "Woh Lamhe",
        "label": "T-Series",
        "label_id": "",
        "origin": "search",
        "is_dolby_content": false,
        "320kbps": "true",
        "encrypted_media_url": "ID2ieOjCrwfgWvL5sXl4B1ImC5QfbsDy0yhCV7/I1zGHL+erEdLoZJdbc2Fq/moab6mkRhRcAym+eM1h/ALaFhw7tS9a8Gtq",
        "encrypted_cache_url": "",
        "encrypted_drm_cache_url": "",
        "encrypted_drm_media_url": "ID2ieOjCrwdjlkMElYlzWCptgNdUpWD8BUZ2fTqaf8fU4HU+EdrPHxwOXBGwDkeuLDBYunKZ/6KAazF5o0HKEY92mytrdt3FDnQW0nglPS4=",
        "album_url": "https://www.jiosaavn.com/s/album/hindi/woh-lamhe-2006/VwYNT6m,Zbs_",
        "duration": "266",
        "rights": {
          "code": "1",
          "cacheable": "true",
          "delete_cached_object": "",
          "reason": "Pro Only"
        },
        "cache_state": "false",
        "has_lyrics": "true",
        "lyrics_snippet": "Lyrics",
        "starred": "false",
        "copyright_text": "℗ 2006 Super Cassettes Industries Private Limited",
        "artistMap": {
          "primary_artists": [],
          "featured_artists": [],
          "artists": []
        }
      },
      "release_date": "",
      "label_url": "/label/t-series-albums/",
      "triller_available": false,
      "request_jiotune_flag": false,
      "webp": "true",
      "lyrics_id": "",
      "button_tooltip_info": [],
      "downloadUrl": [
        {
          "quality": "320kbps",
          "url": "https://aac.saavncdn.com/832/41670273e6110da4b44085d45981aa53_320.mp4"
        },
        {
          "quality": "160kbps",
          "url": "https://aac.saavncdn.com/832/41670273e6110da4b44085d45981aa53_160.mp4"
        },
        {
          "quality": "96kbps",
          "url": "https://aac.saavncdn.com/832/41670273e6110da4b44085d45981aa53_96.mp4"
        },
        {
          "quality": "48kbps",
          "url": "https://aac.saavncdn.com/832/41670273e6110da4b44085d45981aa53_48.mp4"
        },
        {
          "quality": "12kbps",
          "url": "https://aac.saavncdn.com/832/41670273e6110da4b44085d45981aa53_12.mp4"
        }
      ],
      "name": "Kya Mujhe Pyar Hai",
      "artist": "Pritam, KK",
      "album": "Woh Lamhe",
      "primary_artists": "Pritam, KK",
      "duration": "266",
      "encrypted_media_url": "ID2ieOjCrwfgWvL5sXl4B1ImC5QfbsDy0yhCV7/I1zGHL+erEdLoZJdbc2Fq/moab6mkRhRcAym+eM1h/ALaFhw7tS9a8Gtq"
    },
    {
      "id": "QoftRJ-_",
      "title": "Maula Mere Maula",
      "subtitle": "Roopkumar Rathod",
      "header_desc": "",
      "type": "song",
      "perma_url": "https://www.jiosaavn.com/s/song/hindi/pyaar-ki-kashti-mein/maula-mere-maula/IQcNRSZ6Gmw",
      "image": "https://c.saavncdn.com/023/Pyaar-Ki-Kashti-Mein-Hindi-2023-20230213113240-150x150.webp",
      "language": "hindi",
      "year": "2023",
      "play_count": "40550579",
      "explicit_content": "",
      "list_count": "",
      "list_type": "",
      "list": "",
      "more_info": {
        "music": "Roopkumar Rathod, Mithoon",
        "album_id": "42574521",
        "album": "Pyaar Ki Kashti Mein",
        "label": "Saregama",
        "label_id": "",
        "origin": "search",
        "is_dolby_content": false,
        "320kbps": "true",
        "encrypted_media_url": "ID2ieOjCrwfgWvL5sXl4B1ImC5QfbsDyjoqSWY6QzuAbQjCicw9XwwU2Xe9MBHLgvVQ6r/cRyRV7gsYgugBczhw7tS9a8Gtq",
        "encrypted_cache_url": "",
        "encrypted_drm_cache_url": "",
        "encrypted_drm_media_url": "ID2ieOjCrwdjlkMElYlzWCptgNdUpWD8kpuGNn8oQudamEeJ30MOmbW7WCzsHC77g8/pp0MmvflcfhNXmjY4HY92mytrdt3FDnQW0nglPS4=",
        "album_url": "https://www.jiosaavn.com/s/album/hindi/pyaar-ki-kashti-mein-2023/A-vxLMWLwkQ_",
        "duration": "364",
        "rights": {
          "code": "1",
          "cacheable": "true",
          "delete_cached_object": "",
          "reason": "Pro Only"
        },
        "cache_state": "false",
        "has_lyrics": "true",
        "lyrics_snippet": "Aankhen teri...",
        "starred": "false",
        "copyright_text": "℗ 2023 Saregama India Ltd",
        "artistMap": {
          "primary_artists": [],
          "featured_artists": [],
          "artists": []
        }
      },
      "release_date": "",
      "label_url": "/label/saregama-albums/",
      "triller_available": false,
      "request_jiotune_flag": false,
      "webp": "true",
      "lyrics_id": "",
      "button_tooltip_info": [],
      "downloadUrl": [
        {
          "quality": "320kbps",
          "url": "https://aac.saavncdn.com/023/6307e55ffa71a6a95686c3cddd3a9971_320.mp4"
        },
        {
          "quality": "160kbps",
          "url": "https://aac.saavncdn.com/023/6307e55ffa71a6a95686c3cddd3a9971_160.mp4"
        },
        {
          "quality": "96kbps",
          "url": "https://aac.saavncdn.com/023/6307e55ffa71a6a95686c3cddd3a9971_96.mp4"
        },
        {
          "quality": "48kbps",
          "url": "https://aac.saavncdn.com/023/6307e55ffa71a6a95686c3cddd3a9971_48.mp4"
        },
        {
          "quality": "12kbps",
          "url": "https://aac.saavncdn.com/023/6307e55ffa71a6a95686c3cddd3a9971_12.mp4"
        }
      ],
      "name": "Maula Mere Maula",
      "artist": "Roopkumar Rathod",
      "album": "Pyaar Ki Kashti Mein",
      "primary_artists": "Roopkumar Rathod",
      "duration": "364",
      "encrypted_media_url": "ID2ieOjCrwfgWvL5sXl4B1ImC5QfbsDyjoqSWY6QzuAbQjCicw9XwwU2Xe9MBHLgvVQ6r/cRyRV7gsYgugBczhw7tS9a8Gtq"
    },
    {
      "id": "fTyxjlWj",
      "title": "Tere Bina ",
      "subtitle": "A.R. Rahman, Chinmayi, Murtuza Khan, Qadir Khan",
      "header_desc": "",
      "type": "song",
      "perma_url": "https://www.jiosaavn.com/s/song/hindi/perfect-10-ar-rahman-the-spirit-of-music/tere-bina%c2%a0/FjwSSR5cYFk",
      "image": "https://c.saavncdn.com/492/Perfect-10-AR-Rahman-The-Spirit-of-Music-Hindi-2012-20260120201307-150x150.webp",
      "language": "hindi",
      "year": "2012",
      "play_count": "41390437",
      "explicit_content": "",
      "list_count": "",
      "list_type": "",
      "list": "",
      "more_info": {
        "music": "A.R. Rahman",
        "album_id": "12451229",
        "album": "Perfect 10: AR Rahman - The Spirit of Music",
        "label": "Sony Music Entertainment India Pvt. Ltd.",
        "label_id": "",
        "origin": "search",
        "is_dolby_content": false,
        "320kbps": "true",
        "encrypted_media_url": "ID2ieOjCrwfgWvL5sXl4B1ImC5QfbsDyzZs6iHldUwK2ZJFRQB8ghdA7JZ5Iq8GBB37hg46qajClpAIGVgmy5Bw7tS9a8Gtq",
        "encrypted_cache_url": "",
        "encrypted_drm_cache_url": "",
        "encrypted_drm_media_url": "ID2ieOjCrwdjlkMElYlzWCptgNdUpWD8/2qO449RJ6whFbfgSVKT/yqRBLXFu/Qc6pJ9zB+79Uu09ZkBy90tro92mytrdt3FDnQW0nglPS4=",
        "album_url": "https://www.jiosaavn.com/s/album/hindi/perfect-10-ar-rahman-the-spirit-of-music-2012/TnXIhvnHSTQ_",
        "duration": "306",
        "rights": {
          "code": "1",
          "cacheable": "true",
          "delete_cached_object": "",
          "reason": "Pro Only"
        },
        "cache_state": "false",
        "has_lyrics": "false",
        "lyrics_snippet": "",
        "starred": "false",
        "copyright_text": "(P) 2006 Sony Music Entertainment India Pvt. Ltd.",
        "artistMap": {
          "primary_artists": [],
          "featured_artists": [],
          "artists": []
        }
      },
      "release_date": "",
      "label_url": "/label/sony-music-entertainment-india-pvt.-ltd.-albums/",
      "triller_available": false,
      "request_jiotune_flag": false,
      "webp": "true",
      "lyrics_id": "",
      "button_tooltip_info": [],
      "downloadUrl": [
        {
          "quality": "320kbps",
          "url": "https://aac.saavncdn.com/492/886fb62c0a18c51c0a2eca0d6262acd8_320.mp4"
        },
        {
          "quality": "160kbps",
          "url": "https://aac.saavncdn.com/492/886fb62c0a18c51c0a2eca0d6262acd8_160.mp4"
        },
        {
          "quality": "96kbps",
          "url": "https://aac.saavncdn.com/492/886fb62c0a18c51c0a2eca0d6262acd8_96.mp4"
        },
        {
          "quality": "48kbps",
          "url": "https://aac.saavncdn.com/492/886fb62c0a18c51c0a2eca0d6262acd8_48.mp4"
        },
        {
          "quality": "12kbps",
          "url": "https://aac.saavncdn.com/492/886fb62c0a18c51c0a2eca0d6262acd8_12.mp4"
        }
      ],
      "name": "Tere Bina ",
      "artist": "A.R. Rahman, Chinmayi, Murtuza Khan, Qadir Khan",
      "album": "Perfect 10: AR Rahman - The Spirit of Music",
      "primary_artists": "A.R. Rahman, Chinmayi, Murtuza Khan, Qadir Khan",
      "duration": "306",
      "encrypted_media_url": "ID2ieOjCrwfgWvL5sXl4B1ImC5QfbsDyzZs6iHldUwK2ZJFRQB8ghdA7JZ5Iq8GBB37hg46qajClpAIGVgmy5Bw7tS9a8Gtq"
    },
    {
      "id": "Jzpfzszr",
      "title": "Kasoor",
      "subtitle": "Prateek Kuhad",
      "header_desc": "",
      "type": "song",
      "perma_url": "https://www.jiosaavn.com/s/song/hindi/kasoor/kasoor/OhIbVw5DTUE",
      "image": "https://c.saavncdn.com/036/Kasoor-Hindi-2020-20200623224600-150x150.webp",
      "language": "hindi",
      "year": "2020",
      "play_count": "3558499",
      "explicit_content": "",
      "list_count": "",
      "list_type": "",
      "list": "",
      "more_info": {
        "music": "Prateek Kuhad",
        "album_id": "21049724",
        "album": "Kasoor",
        "label": "Prateek Kuhad",
        "label_id": "",
        "origin": "search",
        "is_dolby_content": false,
        "320kbps": "true",
        "encrypted_media_url": "ID2ieOjCrwfgWvL5sXl4B1ImC5QfbsDyqciV2Z7NKUZ2bRatRjoCravX3jKTXRxeGyiLeAmEk5r8l0nLqcyTYhw7tS9a8Gtq",
        "encrypted_cache_url": "",
        "encrypted_drm_cache_url": "",
        "encrypted_drm_media_url": "ID2ieOjCrwdjlkMElYlzWCptgNdUpWD8Dqbq8ces4JoErJpZ+RBFfMDaRbNZ3s4rduqLBGhUW2JgG++Ec79KNY92mytrdt3FDnQW0nglPS4=",
        "album_url": "https://www.jiosaavn.com/s/album/hindi/kasoor-2020/mJA6CW73Nxo_",
        "duration": "197",
        "rights": {
          "code": "1",
          "cacheable": "true",
          "delete_cached_object": "",
          "reason": "Pro Only"
        },
        "cache_state": "false",
        "has_lyrics": "true",
        "lyrics_snippet": "Lyrics",
        "starred": "false",
        "copyright_text": "℗ 2020 Prateek Kuhad",
        "artistMap": {
          "primary_artists": [],
          "featured_artists": [],
          "artists": []
        }
      },
      "release_date": "",
      "label_url": "/label/prateek-kuhad-albums/",
      "triller_available": false,
      "request_jiotune_flag": false,
      "webp": "true",
      "lyrics_id": "",
      "button_tooltip_info": [],
      "downloadUrl": [
        {
          "quality": "320kbps",
          "url": "https://aac.saavncdn.com/036/5ac1b1f1898a2e772191079ae1186e4c_320.mp4"
        },
        {
          "quality": "160kbps",
          "url": "https://aac.saavncdn.com/036/5ac1b1f1898a2e772191079ae1186e4c_160.mp4"
        },
        {
          "quality": "96kbps",
          "url": "https://aac.saavncdn.com/036/5ac1b1f1898a2e772191079ae1186e4c_96.mp4"
        },
        {
          "quality": "48kbps",
          "url": "https://aac.saavncdn.com/036/5ac1b1f1898a2e772191079ae1186e4c_48.mp4"
        },
        {
          "quality": "12kbps",
          "url": "https://aac.saavncdn.com/036/5ac1b1f1898a2e772191079ae1186e4c_12.mp4"
        }
      ],
      "name": "Kasoor",
      "artist": "Prateek Kuhad",
      "album": "Kasoor",
      "primary_artists": "Prateek Kuhad",
      "duration": "197",
      "encrypted_media_url": "ID2ieOjCrwfgWvL5sXl4B1ImC5QfbsDyqciV2Z7NKUZ2bRatRjoCravX3jKTXRxeGyiLeAmEk5r8l0nLqcyTYhw7tS9a8Gtq"
    },
    {
      "id": "Oq_nq_sa",
      "title": "Raat Raazi",
      "subtitle": "Prateek Kuhad",
      "header_desc": "",
      "type": "song",
      "perma_url": "https://www.jiosaavn.com/s/song/hindi/raat-raazi/raat-raazi/Pxk0XwVvRFI",
      "image": "https://c.saavncdn.com/244/Raat-Raazi-Hindi-2013-20260309203000-150x150.webp",
      "language": "hindi",
      "year": "2013",
      "play_count": "1643066",
      "explicit_content": "",
      "list_count": "",
      "list_type": "",
      "list": "",
      "more_info": {
        "music": "",
        "album_id": "73199230",
        "album": "Raat Raazi",
        "label": "Pagal Haina",
        "label_id": "",
        "origin": "search",
        "is_dolby_content": false,
        "320kbps": "true",
        "encrypted_media_url": "ID2ieOjCrwfgWvL5sXl4B1ImC5QfbsDyUcncjnPWSDCyjl4wmb00+WLMZzANZ/abcY10NR9auIAHfvCJy76beRw7tS9a8Gtq",
        "encrypted_cache_url": "",
        "encrypted_drm_cache_url": "",
        "encrypted_drm_media_url": "ID2ieOjCrwdjlkMElYlzWCptgNdUpWD8VyMINXRnNdg1wkDLEmBCmIFiIAhhsZDd5g1KpYrb4LIGctMbT66iK492mytrdt3FDnQW0nglPS4=",
        "album_url": "https://www.jiosaavn.com/s/album/hindi/raat-raazi-2013/akZTtLeux5w_",
        "duration": "287",
        "rights": {
          "code": "1",
          "cacheable": "true",
          "delete_cached_object": "",
          "reason": "Pro Only"
        },
        "cache_state": "false",
        "has_lyrics": "false",
        "lyrics_snippet": "",
        "starred": "false",
        "copyright_text": "© 2013 Pagal Haina",
        "artistMap": {
          "primary_artists": [],
          "featured_artists": [],
          "artists": []
        }
      },
      "release_date": "",
      "label_url": "/label/pagal-haina-albums/",
      "triller_available": false,
      "request_jiotune_flag": false,
      "webp": "true",
      "lyrics_id": "",
      "button_tooltip_info": [],
      "downloadUrl": [
        {
          "quality": "320kbps",
          "url": "https://aac.saavncdn.com/244/ad8f595bfc5a2a9f8176b2377eb511b9_320.mp4"
        },
        {
          "quality": "160kbps",
          "url": "https://aac.saavncdn.com/244/ad8f595bfc5a2a9f8176b2377eb511b9_160.mp4"
        },
        {
          "quality": "96kbps",
          "url": "https://aac.saavncdn.com/244/ad8f595bfc5a2a9f8176b2377eb511b9_96.mp4"
        },
        {
          "quality": "48kbps",
          "url": "https://aac.saavncdn.com/244/ad8f595bfc5a2a9f8176b2377eb511b9_48.mp4"
        },
        {
          "quality": "12kbps",
          "url": "https://aac.saavncdn.com/244/ad8f595bfc5a2a9f8176b2377eb511b9_12.mp4"
        }
      ],
      "name": "Raat Raazi",
      "artist": "Prateek Kuhad",
      "album": "Raat Raazi",
      "primary_artists": "Prateek Kuhad",
      "duration": "287",
      "encrypted_media_url": "ID2ieOjCrwfgWvL5sXl4B1ImC5QfbsDyUcncjnPWSDCyjl4wmb00+WLMZzANZ/abcY10NR9auIAHfvCJy76beRw7tS9a8Gtq"
    },
    {
      "id": "_WVIcEvf",
      "title": "Gul",
      "subtitle": "Anuv Jain",
      "header_desc": "",
      "type": "song",
      "perma_url": "https://www.jiosaavn.com/s/song/hindi/gul/gul/Lz89eBd1QVU",
      "image": "https://c.saavncdn.com/266/Gul-Hindi-2021-20210706151615-150x150.webp",
      "language": "hindi",
      "year": "2021",
      "play_count": "5543278",
      "explicit_content": "",
      "list_count": "",
      "list_type": "",
      "list": "",
      "more_info": {
        "music": "",
        "album_id": "28257912",
        "album": "Gul",
        "label": "Anuv Jain",
        "label_id": "",
        "origin": "search",
        "is_dolby_content": false,
        "320kbps": "true",
        "encrypted_media_url": "ID2ieOjCrwfgWvL5sXl4B1ImC5QfbsDyVhnlMIsAi3G80QKw3I04FdiLJh5w8PSMpmr6VqUyKaQhR7ots2greBw7tS9a8Gtq",
        "encrypted_cache_url": "",
        "encrypted_drm_cache_url": "",
        "encrypted_drm_media_url": "ID2ieOjCrwdjlkMElYlzWCptgNdUpWD817ETHt3ZylxjgFjiqqHeybHOBExzarcsFPFOXE8kbB2+s89WcSRbpI92mytrdt3FDnQW0nglPS4=",
        "album_url": "https://www.jiosaavn.com/s/album/hindi/gul-2021/vLdH-idsObs_",
        "duration": "218",
        "rights": {
          "code": "1",
          "cacheable": "true",
          "delete_cached_object": "",
          "reason": "Pro Only"
        },
        "cache_state": "false",
        "has_lyrics": "false",
        "lyrics_snippet": "",
        "starred": "false",
        "copyright_text": "© 2021 Anuv Jain",
        "artistMap": {
          "primary_artists": [],
          "featured_artists": [],
          "artists": []
        }
      },
      "release_date": "",
      "label_url": "/label/anuv-jain-albums/",
      "triller_available": false,
      "request_jiotune_flag": false,
      "webp": "true",
      "lyrics_id": "",
      "button_tooltip_info": [],
      "downloadUrl": [
        {
          "quality": "320kbps",
          "url": "https://aac.saavncdn.com/266/75a2c612178dea03a50e943310efa85f_320.mp4"
        },
        {
          "quality": "160kbps",
          "url": "https://aac.saavncdn.com/266/75a2c612178dea03a50e943310efa85f_160.mp4"
        },
        {
          "quality": "96kbps",
          "url": "https://aac.saavncdn.com/266/75a2c612178dea03a50e943310efa85f_96.mp4"
        },
        {
          "quality": "48kbps",
          "url": "https://aac.saavncdn.com/266/75a2c612178dea03a50e943310efa85f_48.mp4"
        },
        {
          "quality": "12kbps",
          "url": "https://aac.saavncdn.com/266/75a2c612178dea03a50e943310efa85f_12.mp4"
        }
      ],
      "name": "Gul",
      "artist": "Anuv Jain",
      "album": "Gul",
      "primary_artists": "Anuv Jain",
      "duration": "218",
      "encrypted_media_url": "ID2ieOjCrwfgWvL5sXl4B1ImC5QfbsDyVhnlMIsAi3G80QKw3I04FdiLJh5w8PSMpmr6VqUyKaQhR7ots2greBw7tS9a8Gtq"
    }
  ]
}